{
    "meta": {
        "label": "Language Detection",
        "description": "Detect the dominant language in texts",
        "icon": "icon-comment-alt",
        "iconColor": "orange"
    },
    "kind": "PYTHON",
    "selectableFromDataset": "input_dataset",
    "inputRoles": [
        {
            "name": "input_dataset",
            "label": "Input Dataset",
            "arity": "UNARY",
            "required": true,
            "acceptsDataset": true
        }
    ],
    "outputRoles": [
        {
            "name": "output_dataset",
            "label": "Output Dataset",
            "arity": "UNARY",
            "required": true,
            "acceptsDataset": true
        }
    ],
    "params": [
        {
            "name": "connectionInfo",
            "label": "AWS Connection",
            "type": "PRESET",
            "parameterSetId" : "amazon-comprehend-connection-info",
            "mandatory" : true
        },
        {
            "name": "text_column",
            "label": "Input Text Column",
            "type": "COLUMN",
            "columnRole": "input_dataset",
            "mandatory": true
        },
        {
            "name": "should_output_raw_results",
            "label": "Output Raw Response?",
            "type": "BOOLEAN"
        }
    ]
}
